{
  "id": "hn-20260623-004",
  "title": "AI代理与工程工具平台分析",
  "source_url": "https://www.saturnterminal.com/",
  "source_type": "hackernews",
  "summary": "该网站（Saturn Terminal）可能是一个结合AI代理（AI Agent）与工程工具的平台，旨在简化AI代理的开发、部署和管理流程。其核心亮点可能包括集成式终端环境、自动化工程流程以及针对开发者的友好界面，适用于需要进行AI代理原型设计、调试和运维的场景。由于缺乏具体细节，实际功能需进一步探索。",
  "tags": [
    "ai-agent",
    "engineer",
    "terminal",
    "devops",
    "tools"
  ],
  "score": 6,
  "published_at": "Mon, 22 Jun 2026 19:59:29 +0000",
  "fetched_at": "2026-06-23T11:13:58.797511+00:00",
  "analyzed_at": "2026-06-23T11:15:56.285404+00:00",
  "status": "published"
}